README.md
setup.py
pulumi_ngrok/__init__.py
pulumi_ngrok/_inputs.py
pulumi_ngrok/_utilities.py
pulumi_ngrok/agent_ingress.py
pulumi_ngrok/api_key.py
pulumi_ngrok/certificate_authority.py
pulumi_ngrok/credential.py
pulumi_ngrok/endpoint_configuration.py
pulumi_ngrok/event_destination.py
pulumi_ngrok/event_subscription.py
pulumi_ngrok/ip_policy.py
pulumi_ngrok/ip_policy_rule.py
pulumi_ngrok/ip_restriction.py
pulumi_ngrok/outputs.py
pulumi_ngrok/provider.py
pulumi_ngrok/pulumi-plugin.json
pulumi_ngrok/py.typed
pulumi_ngrok/reserved_address.py
pulumi_ngrok/reserved_domain.py
pulumi_ngrok/ssh_certificate_authority.py
pulumi_ngrok/ssh_credential.py
pulumi_ngrok/ssh_host_certificate.py
pulumi_ngrok/ssh_user_certificate.py
pulumi_ngrok/tls_certificate.py
pulumi_ngrok.egg-info/PKG-INFO
pulumi_ngrok.egg-info/SOURCES.txt
pulumi_ngrok.egg-info/dependency_links.txt
pulumi_ngrok.egg-info/not-zip-safe
pulumi_ngrok.egg-info/requires.txt
pulumi_ngrok.egg-info/top_level.txt
pulumi_ngrok/config/__init__.py
pulumi_ngrok/config/vars.py