Metadata-Version: 2.1
Name: pulumi-ngrok
Version: 0.0.14
Summary: A Pulumi package for creating and managing ngrok cloud resources.
Home-page: https://ngrok.com
License: Apache-2.0
Project-URL: Repository, https://github.com/pierskarsenbarg/pulumi-ngrok
Keywords: pulumi ngrok category/cloud
Platform: UNKNOWN
